Metadata-Version: 1.0
Name: binogauss
Version: 0.1
Summary: Gaussian and Binomial distribution
Home-page: UNKNOWN
Author: geekquad
Author-email: adityaastranaut@gmail.com
License: UNKNOWN
Platform: UNKNOWN
